neuromodcell/Neuron_model_extended.py
neuromodcell/NrnSimulatorParallel.py
neuromodcell/__init__.py
neuromodcell/analysis.py
neuromodcell/experimental_data.py
neuromodcell/model_functions.py
neuromodcell/modulation_functions.py
neuromodcell/modulation_set.py
neuromodcell/optimisation_setup.py
neuromodcell/optimisation_setup_seclamp.py
neuromodcell/optimise.py
neuromodcell/optimise_seclamp.py
neuromodcell/plotting.py
neuromodcell/previous_setup.py
neuromodcell/selection_criteria.py
neuromodcell/selection_functions.py
neuromodcell/utils.py
Neuromodcell-0.2.0.dist-info/LICENSE
Neuromodcell-0.2.0.dist-info/METADATA
Neuromodcell-0.2.0.dist-info/WHEEL
Neuromodcell-0.2.0.dist-info/top_level.txt
Neuromodcell-0.2.0.dist-info/RECORD
