Metadata-Version: 2.1
Name: Neuromodcell
Version: 0.2.0
Summary: Code for optimising for neuromodulation fo single cell NEURON models
Home-page: UNKNOWN
Author: Johanna Frost Nylen
Author-email: johanna.frost.nylen@ki.se
License: UNKNOWN
Platform: UNKNOWN
Classifier: Programming Language :: Python :: 3
Classifier: License :: OSI Approved :: MIT License
Classifier: Operating System :: OS Independent
Requires-Python: >=3.6
License-File: LICENSE
